Workbook

Sheet NGO Research Database
A1: NGO RESEARCH DATABASE — LEADING NGOs OPERATING IN INDIA
A2: Data Analytics Internship Submission | Compiled from Official NGO Websites & Verified Public Sources | July 2026
A4: S.No. | B4: NGO Name | C4: Official Website | D4: Headquarters | E4: State | F4: Country | G4: Year Founded | H4: Founder | I4: Current CEO / Chairperson | J4: Organization Type | K4: Area of Work | L4: Mission | M4: Vision | N4: Major Programs | O4: Key Initiatives | P4: Target Beneficiaries | Q4: States Covered | R4: UN SDGs Supported | S4: Awards / Recognition | T4: Annual Reach | U4: Official Email | V4: Official Phone | W4: LinkedIn Page | X4: Facebook | Y4: Instagram | Z4: Twitter/X | AA4: Data Source | AB4: Last Updated | AC4: Remarks
A5: 1 | B5: Smile Foundation | C5: https://www.smilefoundationindia.org/ | D5: New Delhi | E5: Delhi | F5: India | G5: 2002 | H5: Santanu Mishra (with fellow corporate professionals) | I5: Santanu Mishra (Founder & Executive Trustee) | J5: Registered Trust (NGO) | K5: Education, Healthcare, Livelihood, Women Empowerment | L5: To act as a catalyst for change in the process of inclusive growth of the country by implementing effective grassroots intervention strategies in education, healthcare, livelihood and women empowerment. | M5: Not Publicly Available | N5: Mission Education; Smile on Wheels; Swabhiman (Women Empowerment); STeP (Skills Training for Employment Programme) | O5: Smile Twin e-Learning Program; SIFFCY (Smile International Film Festival for Children & Youth) | P5: Underserved children, youth and women in urban slums and remote villages | Q5: 25-27 states | R5: Not Publicly Available (aligned broadly with SDG 1, 3, 4, 5) | S5: GE Healthcare Modern Medicare Excellence Award (NGO of the Year); Quality Initiative Mission Award 2013 | T5: 20+ lakh (2 million+) children & families annually | U5: Not Publicly Available | V5: Not Publicly Available | W5: https://in.linkedin.com/company/smile-foundation | X5: https://www.facebook.com/smilefoundationindia.org/ | Y5: Not Publicly Available | Z5: Not Publicly Available | AA5: smilefoundationindia.org; en.wikipedia.org/wiki/Smile_Foundation; LinkedIn | AB5: July 2026 | AC5: Pioneer of the Social Venture Philanthropy (SVP) model in India
A6: 2 | B6: CRY - Child Rights and You | C6: https://www.cry.org/ | D6: Mumbai | E6: Maharashtra | F6: India | G6: 1979 | H6: Rippan Kapur | I6: Puja Marwaha (CEO) | J6: Registered NGO (Non-Profit) | K6: Child Rights - Education, Health & Nutrition, Safety & Protection, Child Participation | L6: To ensure happier childhoods for every child in India by protecting and upholding their rights. | M6: A world where every child gets to live, learn, grow and play, and enjoy equal rights | N6: Project Aangan; #YellowFellow; #LearnNotEarn; #ItsAGirlThing; #NotYet | O6: Bal Sanrakshan Samiti handbook (2020); Body Shop India partnership on menstruation awareness | P6: Underprivileged children aged 0-18 years | Q6: 19-20 states | R6: Not Publicly Available | S6: ICAI CSR Award for Best CSR Project 2014; Marketing Excellence Award for Social Awareness 2001; Olga Alexeeva Memorial Prize 2018 (CEO Puja Marwaha) | T6: Impacted over 4.7 million children cumulatively; 21,14,322 children in 2025-26 | U6: Not Publicly Available | V6: Not Publicly Available | W6: https://in.linkedin.com/company/cry | X6: https://www.facebook.com/CRYINDIA | Y6: https://www.instagram.com/cry_india | Z6: https://www.twitter.com/CRYINDIA | AA6: cry.org; en.wikipedia.org/wiki/Child_Rights_and_You; LinkedIn | AB6: July 2026 | AC6: India's oldest and most trusted child rights NGO; works via 144 grassroots project partners
A7: 3 | B7: Pratham Education Foundation | C7: https://www.pratham.org/ | D7: Mumbai | E7: Maharashtra | F7: India | G7: 1995 | H7: Dr. Madhav Chavan & Farida Lambay (Co-Founders) | I7: Dr. Rukmini Banerji (CEO) | J7: Registered Trust (Education NGO) | K7: Education - Early Childhood, Elementary Learning, Foundational Literacy & Numeracy, Youth Skilling | L7: Every Child in School and Learning Well | M7: Not Publicly Available | N7: ASER (Annual Status of Education Report); TaRL (Teaching at the Right Level); Read India; Second Chance; PraDigi Open Learning | O7: Lakhon Mein Ek campaign; CAMaL Ka Camp; Karona (COVID-19 remote learning) | P7: Children, youth and women, especially first-generation learners | Q7: 25-26 states and union territories | R7: Not Publicly Available (aligned broadly with SDG 4 - Quality Education) | S7: WISE Prize for Education 2012; Skoll Award for Social Entrepreneurship 2011; Henry R. Kravis Prize 2010; Yidan Prize 2021; Lui Che Woo Prize 2018 | T7: 7-8 million children and youth annually | U7: Not Publicly Available | V7: Not Publicly Available | W7: Not Publicly Available | X7: Not Publicly Available | Y7: Not Publicly Available | Z7: Not Publicly Available | AA7: pratham.org; en.wikipedia.org/wiki/Pratham; pratham.org/our-story | AB7: July 2026 | AC7: Creator of the globally-adopted ASER citizen-led learning assessment model
A8: 4 | B8: Goonj | C8: https://goonj.org/ | D8: New Delhi | E8: Delhi | F8: India | G8: 1999 | H8: Anshu Gupta & Meenakshi Gupta | I8: Anshu Gupta (Founder-Director) | J8: Registered Society (NGO) | K8: Disaster Relief, Rural Development, Material as a Development Resource | L8: Repositioning cloth and other under-utilised urban material, beyond charity, as a resource for rural development and dignity. | M8: To grow as an idea globally, where material is used mindfully to reach the basics of life to people who need it, without undermining their dignity | N8: Cloth for Work; Rahat (Disaster Relief); School to School; Not Just a Piece of Cloth (NJPC); MY Pad | O8: Green by Goonj (upcycling social enterprise); Gram Swabhimaan | P8: Rural and disaster-affected communities across India | Q8: 23 states | R8: Not Publicly Available | S8: Ramon Magsaysay Award 2015 (Anshu Gupta); World Bank Development Marketplace Award; NASA/US State Dept 'Game Changing Innovation' Award 2012 | T8: 3,500+ tonnes of material processed annually | U8: mail@goonj.org | V8: +91-11-41401216 | W8: Not Publicly Available | X8: Not Publicly Available | Y8: Not Publicly Available | Z8: Not Publicly Available | AA8: goonj.org; en.wikipedia.org/wiki/Goonj_(NGO) | AB8: July 2026 | AC8: Pioneered clothing as a development-sector issue; subject of a Harvard Business School case study
A9: 5 | B9: HelpAge India | C9: https://www.helpageindia.org/ | D9: New Delhi | E9: Delhi | F9: India | G9: 1978 | H9: Founding figures: Cecil Jackson Cole, John F. Pearson, Samson Daniel | I9: Rohit Prasad (CEO) | J9: Registered Society (NGO) | K9: Elderly Welfare - Healthcare, Livelihood, Advocacy | L9: To work for the cause and care of disadvantaged older persons, in order to improve their quality of life. | M9: A society where the elderly have the right to an active, healthy and dignified life | N9: Mobile Healthcare Units (MHU); Cataract Surgeries; Cancer & Palliative Care; Elder Self-Help Groups | O9: Student Action for Value Education (SAVE); Digital Literacy for Elders | P9: Disadvantaged elderly, especially widowed women and BPL seniors | Q9: 22-24 states | R9: Not Publicly Available | S9: UN Population Award 2020; Vayoshreshtha Samman 2014 (Government of India) | T9: Approximately 2 million elderly directly/indirectly every year | U9: Not Publicly Available | V9: +91-11-41688955 | W9: https://in.linkedin.com/company/helpage-india | X9: Not Publicly Available | Y9: Not Publicly Available | Z9: Not Publicly Available | AA9: helpageindia.org; en.wikipedia.org/wiki/HelpAge_India; LinkedIn | AB9: July 2026 | AC9: First and only Indian organisation to win the UN Population Award (2020); founding member of HelpAge International
A10: 6 | B10: CARE India | C10: https://www.careindia.org/ | D10: New Delhi | E10: Delhi | F10: India | G10: 1946 | H10: CARE (Global) entered India via Lincoln Clark, CARE Co-Founder | I10: Rajan Bahadur (Managing Director & CEO) | J10: International NGO (Non-Profit) | K10: Poverty Alleviation, Women & Girls' Empowerment, Health, Livelihoods, Disaster Response | L10: CARE India helps alleviate poverty and social exclusion by facilitating empowerment of women and girls from poor and marginalised communities. | M10: A world of hope, tolerance and social justice, where poverty has been overcome and people live in dignity and security | N10: Health & Nutrition programs; Livelihoods; Education; Disaster/Humanitarian Response | O10: COVID-19 relief response; 'Jhalki' film on child labour awareness (2019) | P10: Poor and marginalised women and girls | Q10: Multiple states including Bihar, Madhya Pradesh, Rajasthan, Tamil Nadu, Maharashtra | R10: Not Publicly Available | S10: Not Publicly Available | T10: Not Publicly Available (Revenue ~US$46.4 million; ~1,100+ employees) | U10: Not Publicly Available | V10: Not Publicly Available | W10: Not Publicly Available | X10: Not Publicly Available | Y10: Not Publicly Available | Z10: Not Publicly Available | AA10: careindia.org; devex.com/organizations/care-india-20251; endslaverynow.org | AB10: July 2026 | AC10: Part of the global CARE confederation; operating in India for over 75 years
A11: 7 | B11: Akshaya Patra Foundation | C11: https://www.akshayapatra.org/ | D11: Bengaluru | E11: Karnataka | F11: India | G11: 2000 | H11: Madhu Pandit Dasa (Founder-Chairman) | I11: Shridhar Venkat (CEO) | J11: Charitable Trust (Registered under Indian Trusts Act 1882) | K11: Mid-Day Meal Programme, Child Nutrition, Education Support | L11: To ensure that no child in India is deprived of education because of hunger, by providing hot, nutritious school meals every school day. | M11: No child in India shall be deprived of education because of hunger | N11: PM POSHAN / Mid-Day Meal Scheme implementation; Anganwadi Feeding Programme; Shakti Kits (maternal nutrition) | O11: COVID-19 Food Relief (250+ million meals); Earthquake relief (Nepal, Turkey) | P11: Government school children; pregnant and lactating mothers | Q11: 16 states and 3 union territories | R11: Not Publicly Available (aligned broadly with SDG 2 and SDG 4) | S11: Gandhi Peace Prize 2016; Nikkei Asia Prize (Economic & Business Innovation); Outlook POSHAN Special Jury Award 2019 | T11: Over 2.25 million children served daily; 4+ billion cumulative meals served | U11: Not Publicly Available | V11: Not Publicly Available | W11: https://in.linkedin.com/company/the-akshaya-patra-foundation | X11: Not Publicly Available | Y11: Not Publicly Available | Z11: Not Publicly Available | AA11: akshayapatra.org; en.wikipedia.org/wiki/Akshaya_Patra_Foundation; LinkedIn | AB11: July 2026 | AC11: World's largest NGO-run school feeding / mid-day meal programme; implementing partner of Govt. of India's PM POSHAN Abhiyaan
A12: 8 | B12: WWF India | C12: https://www.wwfindia.org/ | D12: New Delhi | E12: Delhi | F12: India | G12: 1969 | H12: Founding Group (Charitable Public Trust, est. 27 November 1969) | I12: Ravi Singh (Secretary General & CEO) | J12: Charitable Public Trust (Environmental NGO) | K12: Wildlife & Habitat Conservation, Climate Change, Water Stewardship, Environmental Education | L12: To stop the degradation of the planet's natural environment and build a future in which humans live in harmony with nature. | M12: Building a future in which humans live in harmony with nature | N12: Species conservation (Tiger, Elephant, Rhino, Snow Leopard, Red Panda); River & Wetland Conservation; Climate & Energy | O12: Ek Prithvi environmental education programme; anti-poaching and habitat corridor projects | P12: Wildlife, ecosystems and dependent local communities | Q12: 20+ states (60+ state/field offices) | R12: Not Publicly Available (aligned broadly with SDG 13, 14, 15) | S12: Not Publicly Available (part of the globally recognised WWF network) | T12: Not Publicly Available | U12: Not Publicly Available | V12: Not Publicly Available | W12: Not Publicly Available | X12: Not Publicly Available | Y12: Not Publicly Available | Z12: Not Publicly Available | AA12: wwfindia.org; en.wikipedia.org/wiki/WWF-India | AB12: July 2026 | AC12: India's largest voluntary body in the field of wildlife/nature conservation; part of the WWF International network (100+ countries)
A13: 9 | B13: GiveIndia | C13: https://www.giveindia.org/ | D13: Mumbai / Bengaluru | E13: Maharashtra / Karnataka | F13: India | G13: 2000 | H13: Venkat Krishnan (conceived 1999, registered as Give Foundation April 2000) | I13: Atul Satija (Founder & CEO) | J13: Not-for-Profit Company (Sec. 8, Companies Act) - Giving/Crowdfunding Platform | K13: Philanthropy Platform - Crowdfunding, Corporate Giving, NGO Due-Diligence & Grants | L13: GiveIndia exists to alleviate poverty by delivering impactful social initiatives and enabling the world to give. | M13: A poverty-free India built on a strong culture of trusted giving | N13: Crowdfunding platform; Corporate Giving & CSR consulting; Monthly Giving programmes (No Child Hungry, #EldersLivesMatter) | O13: 10 million mid-day meals initiative; Joy of Giving Week / Daan Utsav | P13: Beneficiaries of 2,500+ vetted partner NGOs across India | Q13: 23 states | R13: Not Publicly Available (aligned broadly with SDG 1 and SDG 17) | S13: Not Publicly Available | T13: 15 million+ people impacted via network; 2 million+ donors; 300+ crore in contributions channeled | U13: Not Publicly Available | V13: Not Publicly Available | W13: Not Publicly Available | X13: Not Publicly Available | Y13: Not Publicly Available | Z13: Not Publicly Available | AA13: giveindia.org; crunchbase.com/organization/giveindia; tracxn.com | AB13: July 2026 | AC13: India's largest and most trusted online giving/crowdfunding platform, funded to zero-transaction-cost model by ICICI Bank grant
A14: 10 | B14: SEWA (Self Employed Women's Association) | C14: https://www.sewa.org/ | D14: Ahmedabad | E14: Gujarat | F14: India | G14: 1972 | H14: Ela Bhatt (Elaben Bhatt) | I14: Reema Nanavaty (General Secretary) | J14: Registered Trade Union (NGO) | K14: Women's Economic Empowerment, Informal Sector Labour Rights | L14: To organise women workers in the informal economy for full employment and self-reliance, securing work, income, food and social security. | M14: Swachh Akash (Clean Skies) - a just, climate-resilient future for informal women workers and their communities | N14: SEWA Bank (est. 1974); SEWA Academy; Trade Cooperatives (agriculture, dairy, handicrafts); Healthcare & Childcare services | O14: Swachh Akash climate initiative; Parametric heat-insurance policy for informal women workers (2024) | P14: Self-employed and informal-sector women workers | Q14: 18-20 states | R14: Not Publicly Available (aligned broadly with SDG 1, 5, 8) | S14: Ramon Magsaysay Award 1977 (Ela Bhatt); Right Livelihood Award; Niwano Peace Prize 2010 | T14: 3.78 million members | U14: Not Publicly Available | V14: Not Publicly Available | W14: Not Publicly Available | X14: Not Publicly Available | Y14: Not Publicly Available | Z14: Not Publicly Available | AA14: sewa.org; en.wikipedia.org/wiki/Self_Employed_Women's_Association; sewabharat.org | AB14: July 2026 | AC14: Single largest national trade union of informal-economy women workers in India; ILO-recognised labour union

Sheet Data Analysis
A1: DATA ANALYSIS — NGO RESEARCH DATABASE
A3: 1. TOTAL NGOs RESEARCHED
A4: Total NGOs in Database | B4: =COUNTA('NGO Research Database'!B5:B14) -> 10
A6: 2. ORGANIZATION TYPE DISTRIBUTION
A7: Organization Type | B7: Count
A8: Registered Trust | B8: =COUNTIF('NGO Research Database'!J5:J14,"*"&A8&"*") -> 2
A9: Registered NGO | B9: =COUNTIF('NGO Research Database'!J5:J14,"*"&A9&"*") -> 1
A10: Registered Society | B10: =COUNTIF('NGO Research Database'!J5:J14,"*"&A10&"*") -> 2
A11: International NGO | B11: =COUNTIF('NGO Research Database'!J5:J14,"*"&A11&"*") -> 1
A12: Charitable Trust | B12: =COUNTIF('NGO Research Database'!J5:J14,"*"&A12&"*") -> 1
A13: Charitable Public Trust | B13: =COUNTIF('NGO Research Database'!J5:J14,"*"&A13&"*") -> 1
A14: Not-for-Profit Company | B14: =COUNTIF('NGO Research Database'!J5:J14,"*"&A14&"*") -> 1
A15: Registered Trade Union | B15: =COUNTIF('NGO Research Database'!J5:J14,"*"&A15&"*") -> 1
A17: 3. HEADQUARTERS STATE-WISE DISTRIBUTION
A18: State | B18: Count
A19: Delhi | B19: =COUNTIF('NGO Research Database'!E5:E14,"*"&A19&"*") -> 5
A20: Maharashtra | B20: =COUNTIF('NGO Research Database'!E5:E14,"*"&A20&"*") -> 3
A21: Karnataka | B21: =COUNTIF('NGO Research Database'!E5:E14,"*"&A21&"*") -> 2
A22: Gujarat | B22: =COUNTIF('NGO Research Database'!E5:E14,"*"&A22&"*") -> 1
A24: 4. FOUNDED YEAR (DECADE) ANALYSIS
A25: Decade | B25: NGOs Founded
A26: 1940s | B26: =COUNTIFS('NGO Research Database'!G5:G14,">="&1940,'NGO Research Database'!G5:G14,"<="&1949) -> 1
A27: 1960s | B27: =COUNTIFS('NGO Research Database'!G5:G14,">="&1960,'NGO Research Database'!G5:G14,"<="&1969) -> 1
A28: 1970s | B28: =COUNTIFS('NGO Research Database'!G5:G14,">="&1970,'NGO Research Database'!G5:G14,"<="&1979) -> 3
A29: 1990s | B29: =COUNTIFS('NGO Research Database'!G5:G14,">="&1990,'NGO Research Database'!G5:G14,"<="&1999) -> 2
A30: 2000s | B30: =COUNTIFS('NGO Research Database'!G5:G14,">="&2000,'NGO Research Database'!G5:G14,"<="&2009) -> 3
A33: Oldest NGO (by Year Founded) | B33: =INDEX('NGO Research Database'!B5:B14,MATCH(MIN('NGO Research Database'!G5:G14),'NGO Research Database'!G5:G14,0)) -> CARE India
A34: Newest NGO (by Year Founded) | B34: =INDEX('NGO Research Database'!B5:B14,MATCH(MAX('NGO Research Database'!G5:G14),'NGO Research Database'!G5:G14,0)) -> Smile Foundation
A35: Average NGO Age (Years, as of 2026) | B35: =2026-AVERAGE('NGO Research Database'!G5:G14) -> 42
A37: 5. AREA OF WORK / FOCUS AREA DISTRIBUTION
A38: Focus Area | B38: NGOs Working In Area
A39: Education | B39: =COUNTIF('NGO Research Database'!K5:K14,"*"&A39&"*") -> 5
A40: Healthcare | B40: =COUNTIF('NGO Research Database'!K5:K14,"*"&A40&"*") -> 2
A41: Health | B41: =COUNTIF('NGO Research Database'!K5:K14,"*"&A41&"*") -> 4
A42: Livelihood | B42: =COUNTIF('NGO Research Database'!K5:K14,"*"&A42&"*") -> 3
A43: Women Empowerment | B43: =COUNTIF('NGO Research Database'!K5:K14,"*"&A43&"*") -> 1
A44: Child Rights | B44: =COUNTIF('NGO Research Database'!K5:K14,"*"&A44&"*") -> 1
A45: Elderly Welfare | B45: =COUNTIF('NGO Research Database'!K5:K14,"*"&A45&"*") -> 1
A46: Environmental Conservation | B46: =COUNTIF('NGO Research Database'!K5:K14,"*"&A46&"*") -> 0
A47: Disaster Relief | B47: =COUNTIF('NGO Research Database'!K5:K14,"*"&A47&"*") -> 1
A48: Rural Development | B48: =COUNTIF('NGO Research Database'!K5:K14,"*"&A48&"*") -> 1
A49: Nutrition | B49: =COUNTIF('NGO Research Database'!K5:K14,"*"&A49&"*") -> 2
A50: Poverty Alleviation | B50: =COUNTIF('NGO Research Database'!K5:K14,"*"&A50&"*") -> 1
A53: 6. TOP FOCUS AREAS (RANKED)
A54: Rank | B54: Focus Area (Highest Frequency)
A55: 1 | B55: =INDEX($A$39:$A$50,MATCH(LARGE($B$39:$B$50,1),$B$39:$B$50,0)) -> Education
A56: 2 | B56: =INDEX($A$39:$A$50,MATCH(LARGE($B$39:$B$50,2),$B$39:$B$50,0)) -> Health
A57: 3 | B57: =INDEX($A$39:$A$50,MATCH(LARGE($B$39:$B$50,3),$B$39:$B$50,0)) -> Livelihood
A58: 4 | B58: =INDEX($A$39:$A$50,MATCH(LARGE($B$39:$B$50,4),$B$39:$B$50,0)) -> Healthcare
A59: 5 | B59: =INDEX($A$39:$A$50,MATCH(LARGE($B$39:$B$50,5),$B$39:$B$50,0)) -> Healthcare
A61: 7. MISSION STATEMENT — TOP KEYWORDS
A62: Keyword | B62: Frequency (across 10 mission statements)
A63: Women | B63: 3
A64: Child | B64: 3
A65: India | B65: 3
A66: School | B66: 3
A67: Social | B67: 3
A68: Education | B68: 2
A69: Empowerment | B69: 2
A70: Ensure | B70: 2
A71: Work | B71: 2
A72: Care | B72: 2
A75: 8. KEY INSIGHTS
A76: 1. Education (Pratham, Smile Foundation, CRY, Akshaya Patra) is the single most represented focus area across the dataset, reflecting the sector's national priority on foundational learning.
A77: 2. Delhi/NCR is the most common headquarters location (4 of 10 NGOs), reinforcing its status as India's non-profit administrative hub.
A78: 3. Half of the surveyed NGOs were founded in the 1970s-1990s, indicating a wave of institution-building in India's early civil-society movement, distinct from the more recent 2000s wave (GiveIndia, Akshaya Patra).
A79: 4. Women's empowerment is a cross-cutting theme, appearing explicitly in the mandates of CARE India, SEWA, and Smile Foundation, beyond dedicated single-issue NGOs.
A80: 5. Several NGOs (CRY, Pratham, Goonj, HelpAge India, SEWA) were founded by individual social entrepreneurs who remain closely associated with the brand, while others (CARE India, WWF India) are Indian chapters of global federations.
A81: 6. Contact-level data (official email/phone) is largely unavailable in public domain sources, consistent with most Indian NGOs directing donor/public queries through web contact forms rather than publishing direct emails.
A83: 9. RECOMMENDATIONS
A84: 1. Prioritise CSR partnerships with NGOs whose focus areas (education, health, livelihood) align most closely with corporate ESG themes for higher grant-utilisation efficiency.
A85: 2. Encourage NGOs lacking published SDG mappings to formally publish SDG alignment, improving transparency for institutional and international donors.
A86: 3. Support smaller/newer NGOs (2000s cohort) in building the multi-decade brand trust that older organisations (CRY, HelpAge India, SEWA) have achieved.
A87: 4. Recommend NGOs publish standardised public contact details (official email/phone) to improve donor and researcher accessibility.
... A91: This analysis profiles 10 leading NGOs operating in India across education, child rights, elderly welfare, women's empowerment, environment, nutrition, disaster relief and philanthropic intermediation. Collectively, these organisations were founded between 1946 and 2002, are headquartered predominantly in Delhi-NCR, Mumbai and Bengaluru, and together reach tens of millions of beneficiaries annually. The dataset demonstrates a mature, diversified Indian non-profit sector with strong founder-led legacies and increasing formalisation via governance boards, CEOs and verifiable public reporting.

Sheet Dashboard
A1: NGO RESEARCH — EXECUTIVE DASHBOARD
A3: 10 Leading NGOs Operating in India | Data Analytics Internship Submission | July 2026
B5: TOTAL NGOs RESEARCHED | E5: UNIQUE HQ STATES | H5: FOCUS AREAS TRACKED | K5: ORGANIZATION CATEGORIES
B9: ='Data Analysis'!B4 -> 10 | E9: =SUMPRODUCT(('Data Analysis'!B19:B22>0)*1) -> 4 | H9: =SUMPRODUCT(('Data Analysis'!B39:B50>0)*1) -> 11 | K9: =SUMPRODUCT(('Data Analysis'!B8:B15>0)*1) -> 8

Sheet Data Dictionary
A1: DATA DICTIONARY — NGO RESEARCH DATABASE
A3: Column Name | B3: Meaning | C3: Data Type | D3: Source
A4: S.No. | B4: Sequential row identifier for each NGO record. | C4: Integer | D4: Internal / Assigned
A5: NGO Name | B5: Official registered/brand name of the organization. | C5: Text | D5: Official Website
A6: Official Website | B6: Primary official URL of the NGO (hyperlinked). | C6: URL (Text) | D6: Official Website
A7: Headquarters | B7: City where the NGO's head/registered office is located. | C7: Text | D7: Official Website / Wikipedia
A8: State | B8: Indian state in which the headquarters is located. | C8: Text | D8: Official Website / Wikipedia
A9: Country | B9: Country of registration/operation (India for all records). | C9: Text | D9: Official Website
A10: Year Founded | B10: Calendar year the organization was established/registered. | C10: Integer (Year) | D10: Official Website / Wikipedia
A11: Founder | B11: Individual(s) credited with founding the organization. | C11: Text | D11: Official Website / Wikipedia
A12: Current CEO / Chairperson | B12: Name and title of the current chief executive or chairperson, where publicly available. | C12: Text | D12: Official Website / LinkedIn
A13: Organization Type | B13: Legal/structural classification (Trust, Society, Sec.8 Company, etc.). | C13: Text (Category) | D13: Official Website / Registrar records
A14: Area of Work | B14: Primary thematic sector(s) the NGO operates in. | C14: Text (Category) | D14: Official Website
... A32: Remarks | B32: Additional notable facts or context about the NGO. | C32: Text | D32: Compiled by Researcher

Sheet About the Author
A1: ABOUT THE AUTHOR
A3: Name | B3: Mohd Azeem
A4: College | B4: Teerthanker Mahaveer University (TMU)
A5: Mobile | B5: +91 7088614740
A6: LinkedIn | B6: https://www.linkedin.com/in/mohd-azeem-597a55230
A7: Role | B7: Data Analytics Intern
A9: SKILLS DEMONSTRATED
A10: ● | B10: Business Research
A11: ● | B11: Data Collection
A12: ● | B12: Data Cleaning
A13: ● | B13: Excel (Formulas, Pivot Logic, Conditional Formatting)
A14: ● | B14: Dashboard Design
A15: ● | B15: Data Visualization
A16: ● | B16: Analytical Thinking
A17: ● | B17: Professional Reporting
A19: This workbook was researched, compiled, analyzed, and designed by Mohd Azeem as part of a Data Analytics Internship assignment, using verified data from official NGO websites and trusted public sources.
